shotgrid_flow/__init__.py
shotgrid_flow/flow.py
shotgrid_flow/version.py
shotgrid_flow-0.1.0.dist-info/LICENSE
shotgrid_flow-0.1.0.dist-info/METADATA
shotgrid_flow-0.1.0.dist-info/WHEEL
shotgrid_flow-0.1.0.dist-info/RECORD
