Metadata-Version: 2.3
Name: shotgrid-flow
Version: 0.1.0
Summary: A simple connection maker for ShotGrid
License: MIT
Author: mswed
Author-email: mswed@beapot.com
Requires-Python: >=3.9,<=3.11
Classifier: License :: OSI Approved :: MIT License
Classifier: Programming Language :: Python :: 3
Classifier: Programming Language :: Python :: 3.9
Classifier: Programming Language :: Python :: 3.10
Classifier: Programming Language :: Python :: 3.11
Requires-Dist: python-dotenv (>=1.1.0,<2.0.0)
Requires-Dist: sgtk (>=0.21.7,<0.22.0)
